AUTHORS
CHANGES
LICENSE
MANIFEST.in
README.rst
conftest.py
setup.py
django_uuid_pk/__init__.py
django_uuid_pk/fields.py
django_uuid_pk/models.py
django_uuid_pk/requirements.pip
django_uuid_pk.egg-info/PKG-INFO
django_uuid_pk.egg-info/SOURCES.txt
django_uuid_pk.egg-info/dependency_links.txt
django_uuid_pk.egg-info/not-zip-safe
django_uuid_pk.egg-info/requires.txt
django_uuid_pk.egg-info/top_level.txt
django_uuid_pk/tests/.coveragerc
django_uuid_pk/tests/__init__.py
django_uuid_pk/tests/ddf.py
django_uuid_pk/tests/models.py
django_uuid_pk/tests/settings.py
django_uuid_pk/tests/tests.py