Metadata-Version: 1.1
Name: django-uuid-pk
Version: 0.2
Summary: Django UUIDField with full primary-key protocol support
Home-page: https://github.com/saxix/django-uuid-pk
Author: sax
Author-email: sax@os4d.org
License: BSD
Download-URL: https://github.com/saxix/django-uuid-pk
Platform: any
Classifier: Environment :: Web Environment
Classifier: Framework :: Django
Classifier: Operating System :: OS Independent
Classifier: Programming Language :: Python
Classifier: Intended Audience :: Developers
